qsimkit/VERSION
qsimkit/__init__.py
qsimkit/_version.py
qsimkit/bounds.py
qsimkit/channel.py
qsimkit/debug.ipynb
qsimkit/fermion.py
qsimkit/measure.py
qsimkit/plot_config.py
qsimkit/spin.py
qsimkit/states.py
qsimkit/test.ipynb
qsimkit/trotter.py
qsimkit/utils.py
qsimkit/version.py
qsimkit/visualization.ipynb
qsimkit/data/hydrogen_2_1.0.hdf5
qsimkit-0.1.15.dist-info/licenses/LICENSE
qsimkit-0.1.15.dist-info/METADATA
qsimkit-0.1.15.dist-info/WHEEL
qsimkit-0.1.15.dist-info/entry_points.txt
qsimkit-0.1.15.dist-info/top_level.txt
qsimkit-0.1.15.dist-info/RECORD
