Metadata-Version: 2.4
Name: qsimkit
Version: 0.1.15
Summary: Quantum Simulation Toolkit - Error bounds and Trotterization tools
Author-email: Jue XU <xujue@connect.hku.hk>
License-Expression: Apache-2.0
Project-URL: Homepage, https://github.com/Jue-Xu/Qsimkit
Project-URL: Repository, https://github.com/Jue-Xu/Qsimkit
Project-URL: Documentation, https://jue-xu.github.io/cookbook-quantum-simulation
Classifier: Programming Language :: Python :: 3
Classifier: Development Status :: 4 - Beta
Classifier: Intended Audience :: Science/Research
Classifier: Topic :: Scientific/Engineering :: Physics
Requires-Python: >=3.10
License-File: LICENSE
Requires-Dist: qiskit>=1.0.2
Requires-Dist: qiskit-aer>=0.17.2
Requires-Dist: jaxlib>=0.6.2
Requires-Dist: jax>=0.6.2
Requires-Dist: openfermion>=1.5.1
Requires-Dist: openfermionpyscf>=0.5
Requires-Dist: matplotlib>=3.8.2
Requires-Dist: numpy>=1.23.5
Requires-Dist: pandas>=2.2.2
Requires-Dist: scipy>=1.12.0
Requires-Dist: colorspace>=1.0.0
Requires-Dist: multiprocess>=0.70.16
Dynamic: license-file
